hydro_event_detector/.ipynb_checkpoints/__init__-checkpoint.py
hydro_event_detector/__init__.py
hydro_event_detector-0.1.0.dist-info/LICENSE
hydro_event_detector-0.1.0.dist-info/METADATA
hydro_event_detector-0.1.0.dist-info/WHEEL
hydro_event_detector-0.1.0.dist-info/RECORD
